flake8_ruler/__init__.py
flake8_ruler/__main__.py
flake8_ruler/_cli.py
flake8_ruler/_config.py
flake8_ruler/_ini.py
flake8_ruler/_rules.py
flake8_ruler-0.1.0.dist-info/LICENSE
flake8_ruler-0.1.0.dist-info/WHEEL
flake8_ruler-0.1.0.dist-info/METADATA
flake8_ruler-0.1.0.dist-info/RECORD
