Metadata-Version: 2.1
Name: flake8_ruler
Version: 0.1.0
Summary: More powerful configs for flake8.
Keywords: flake8,pyproject.toml,flakehell
Author-email: Gram <gram@orsinium.dev>
Requires-Python: >=3.6
Classifier: Development Status :: 5 - Production/Stable
Classifier: Environment :: Plugins
Classifier: Intended Audience :: Developers
Classifier: License :: OSI Approved :: MIT License
Classifier: Programming Language :: Python
Classifier: Topic :: Software Development
Classifier: Topic :: Software Development :: Quality Assurance
Requires-Dist: flake8
Requires-Dist: flake8-codes
Requires-Dist: urllib3
Requires-Dist: wemake-python-styleguide ; extra == "lint"
Requires-Dist: unify ; extra == "lint"
Requires-Dist: isort ; extra == "lint"
Requires-Dist: pytest ; extra == "test"
Project-URL: Source, https://github.com/orsinium-labs/flake8-ruler
Provides-Extra: lint
Provides-Extra: test
